{"cameraMode":{"drawMode":0,"name":"Shaded","section":"Shading Mode"},"sceneLighting":true,"audioPlay":false,"sceneViewState":{"m_AlwaysRefresh":false,"showFog":true,"showSkybox":true,"showFlares":true,"showImageEffects":true,"showParticleSystems":true,"showVisualEffectGraphs":true,"m_FxEnabled":true},"in2DMode":false,"pivot":{"x":1182.5037841796875,"y":-2418.973876953125,"z":1661.6427001953125},"rotation":{"x":0.4010908007621765,"y":0.2784269452095032,"z":-0.1294921338558197,"w":0.8632133603096008},"size":1604.5263671875,"orthographic":false}